wordreference_scraper/__init__.py
wordreference_scraper/wordreference_scraper.py
wordreference_scraper-0.1.1.dist-info/LICENSE
wordreference_scraper-0.1.1.dist-info/WHEEL
wordreference_scraper-0.1.1.dist-info/METADATA
wordreference_scraper-0.1.1.dist-info/RECORD
