Metadata-Version: 2.1
Name: wordreference-scraper
Version: 0.1.1
Summary: Scraping words from wordreference.com
License: MIT
Author: Santiago Padron
Requires-Python: >=3.8,<4
Classifier: License :: OSI Approved :: MIT License
Classifier: Programming Language :: Python :: 3
Classifier: Programming Language :: Python :: 3.10
Classifier: Programming Language :: Python :: 3.8
Classifier: Programming Language :: Python :: 3.9
Requires-Dist: beautifulsoup4 (>=4.11.1)
Requires-Dist: requests (>=2.28.1)
